modfixer/__init__.py
modfixer/__main__.py
modfixer/builder.py
modfixer/unbuilder.py
ModFixer-1.0.0.dist-info/METADATA
ModFixer-1.0.0.dist-info/WHEEL
ModFixer-1.0.0.dist-info/entry_points.txt
ModFixer-1.0.0.dist-info/top_level.txt
ModFixer-1.0.0.dist-info/RECORD
