Metadata-Version: 2.1
Name: ModFixer
Version: 1.0.0
Summary: CLI for on the fly GFX packing to load as a Cemu graphic pack for quick and efficient testing.
Home-page: https://github.com/ArchLeaders/ModFixer
Author: ArchLeaders
Author-email: archleadership28@gmail.com
Classifier: Development Status :: 4 - Beta
Classifier: Environment :: Console
Classifier: License :: OSI Approved :: GNU General Public License v3 or later (GPLv3+)
Classifier: Operating System :: OS Independent
Classifier: Programming Language :: Python :: 3 :: Only
Requires-Python: >=3.7
Requires-Dist: rstb (>=1.2.2)
Requires-Dist: bcml (>=3.8.6)
Requires-Dist: oead (~=1.2.0)
